git_regex_search/__init__.py
git_regex_search/git_regex_search.py
git_regex_search-1.dist-info/METADATA
git_regex_search-1.dist-info/WHEEL
git_regex_search-1.dist-info/top_level.txt
git_regex_search-1.dist-info/RECORD
