Metadata-Version: 2.1
Name: git-regex-search
Version: 1
Summary: This program allows you to search for a specific pattern within the files of a GitHub repository(using PyGithub).
Author: Aviksaikat (Saikat Karmakar)
Author-email: <aviksaikat@gmail.com>
Classifier: Development Status :: 1 - Planning
Classifier: Intended Audience :: Education
Classifier: Programming Language :: Python :: 3
Classifier: Operating System :: Unix
Classifier: Operating System :: MacOS :: MacOS X
Classifier: Operating System :: Microsoft :: Windows
Requires-Dist: PyGithub
Requires-Dist: re
Requires-Dist: termcolor
Requires-Dist: toml
